tool.py
jalib/__init__.py
jalib/jalib1.py
jalib-1.0.0.dist-info/DESCRIPTION.rst
jalib-1.0.0.dist-info/METADATA
jalib-1.0.0.dist-info/RECORD
jalib-1.0.0.dist-info/WHEEL
jalib-1.0.0.dist-info/metadata.json
jalib-1.0.0.dist-info/top_level.txt
