Metadata-Version: 2.0
Name: jalib
Version: 1.0.0
Summary: just a test lib
Home-page: https://github.com
Author: jacob
Author-email: 312846421@qq.com
License: MIT
Platform: UNKNOWN
